oakkeeper/__init__.py
oakkeeper/__main__.py
oakkeeper/api.py
oakkeeper/cli.py
oakkeeper/zappr.py
oakkeeper-1.1.3.dist-info/DESCRIPTION.rst
oakkeeper-1.1.3.dist-info/METADATA
oakkeeper-1.1.3.dist-info/RECORD
oakkeeper-1.1.3.dist-info/WHEEL
oakkeeper-1.1.3.dist-info/entry_points.txt
oakkeeper-1.1.3.dist-info/metadata.json
oakkeeper-1.1.3.dist-info/top_level.txt
