Metadata-Version: 2.0
Name: oakkeeper
Version: 1.1.3
Summary: CLI to set branch protection of a Github repository in a Zalando-compliant way
Home-page: https://github.com/zalando-incubator/oakkeeper
Author: Nikolaus Piccolotto
Author-email: nikolaus.piccolotto@zalando.de
License: UNKNOWN
Download-URL: https://github.com/zalando-incubator/oakkeeper/tarball/1.1.3
Platform: UNKNOWN
Requires-Dist: click
Requires-Dist: clickclick
Requires-Dist: requests
